astrotool/__init__.py
astrotool/angles.py
astrotool/binaries.py
astrotool/cli_scripts.py
astrotool/coordinates.py
astrotool/cosmology.py
astrotool/date_time.py
astrotool/gws.py
astrotool/light.py
astrotool/magnitudes.py
astrotool/stars.py
astrotool/visibility.py
astrotool-0.0.26.dist-info/licenses/LICENCE
astrotool-0.0.26.dist-info/METADATA
astrotool-0.0.26.dist-info/WHEEL
astrotool-0.0.26.dist-info/entry_points.txt
astrotool-0.0.26.dist-info/top_level.txt
astrotool-0.0.26.dist-info/RECORD
