Metadata-Version: 2.4
Name: astrotool
Version: 0.0.26
Summary: A Python package for astronomical calculations in Python or on the command line
Author-email: Marc van der Sluys <git@vandersluys.nl>
License-Expression: EUPL-1.2
Project-URL: GitHub, https://github.com/MarcvdSluys/AstroTool
Project-URL: ReadTheDocs, https://astrotool.readthedocs.io
Project-URL: Homepage, https://www.nikhef.nl/~sluys/AstroTool
Keywords: astronomy,ephemeris,date,time,coordinates
Classifier: Development Status :: 3 - Alpha
Classifier: Intended Audience :: Developers
Classifier: Intended Audience :: Education
Classifier: Intended Audience :: Science/Research
Classifier: Natural Language :: English
Classifier: Operating System :: OS Independent
Classifier: Programming Language :: Python :: 3
Classifier: Topic :: Scientific/Engineering :: Astronomy
License-File: LICENCE
Requires-Dist: astroconst
Requires-Dist: colored_traceback
Requires-Dist: numpy
Requires-Dist: pandas
Requires-Dist: scipy
Dynamic: license-file
